fragmentedmp4stream/__init__.py
fragmentedmp4stream/reader.py
fragmentedmp4stream/segmenter.py
fragmentedmp4stream/service.py
fragmentedmp4stream/writer.py
fragmentedmp4stream/atom/__init__.py
fragmentedmp4stream/atom/atom.py
fragmentedmp4stream/atom/avcc.py
fragmentedmp4stream/atom/co64.py
fragmentedmp4stream/atom/ctts.py
fragmentedmp4stream/atom/dref.py
fragmentedmp4stream/atom/esds.py
fragmentedmp4stream/atom/fiel.py
fragmentedmp4stream/atom/ftyp.py
fragmentedmp4stream/atom/hdlr.py
fragmentedmp4stream/atom/hvcc.py
fragmentedmp4stream/atom/mdat.py
fragmentedmp4stream/atom/mdhd.py
fragmentedmp4stream/atom/mfhd.py
fragmentedmp4stream/atom/mvhd.py
fragmentedmp4stream/atom/pasp.py
fragmentedmp4stream/atom/smhd.py
fragmentedmp4stream/atom/stco.py
fragmentedmp4stream/atom/stsc.py
fragmentedmp4stream/atom/stsd.py
fragmentedmp4stream/atom/stsz.py
fragmentedmp4stream/atom/stts.py
fragmentedmp4stream/atom/tfhd.py
fragmentedmp4stream/atom/tkhd.py
fragmentedmp4stream/atom/trex.py
fragmentedmp4stream/atom/trun.py
fragmentedmp4stream/atom/vmhd.py
fragmented_mp4stream_pkg-0.0.3.dist-info/LICENSE
fragmented_mp4stream_pkg-0.0.3.dist-info/METADATA
fragmented_mp4stream_pkg-0.0.3.dist-info/WHEEL
fragmented_mp4stream_pkg-0.0.3.dist-info/top_level.txt
fragmented_mp4stream_pkg-0.0.3.dist-info/RECORD
