Metadata-Version: 2.1
Name: fragmented-mp4stream-pkg
Version: 0.0.3
Summary: Service to stream mp4 files in fragments
Home-page: https://github.com/m-khomutov/pyfmp4
Author: mkh
Author-email: m.khomutov@list.ru
License: UNKNOWN
Project-URL: Bug Tracker, https://github.com/m-khomutov/pyfmp4/issues
Platform: UNKNOWN
Classifier: Programming Language :: Python :: 3
Classifier: License :: OSI Approved :: MIT License
Classifier: Operating System :: OS Independent
Requires-Python: >=3.6
